piweatherrock/data_climacell/__init__.py
piweatherrock/data_climacell/pwr_data.py
piweatherrock_data_climacell-0.2.2.data/scripts/pwr-climacell-data
piweatherrock_data_climacell-0.2.2.dist-info/LICENSE
piweatherrock_data_climacell-0.2.2.dist-info/METADATA
piweatherrock_data_climacell-0.2.2.dist-info/WHEEL
piweatherrock_data_climacell-0.2.2.dist-info/top_level.txt
piweatherrock_data_climacell-0.2.2.dist-info/RECORD
