Metadata-Version: 2.1
Name: piweatherrock-data-climacell
Version: 0.2.2
Summary: Provides forecast data from ClimaCell for PiWeatherRock
Home-page: https://github.com/genebean/piweatherrock-data-climacell
Author: Gene Liverman
Author-email: gene@technicalissues.us
License: MIT
Platform: UNKNOWN
Classifier: License :: OSI Approved :: MIT License
Requires-Python: >=3.7
Requires-Dist: requests (==2.23.0)
